MANIFEST.in
README.md
setup.py
src/githubflow/__init__.py
src/githubflow/authenticate.py
src/githubflow/github.py
src/githubflow/runner.py
src/githubflow.egg-info/PKG-INFO
src/githubflow.egg-info/SOURCES.txt
src/githubflow.egg-info/dependency_links.txt
src/githubflow.egg-info/entry_points.txt
src/githubflow.egg-info/requires.txt
src/githubflow.egg-info/top_level.txt