Metadata-Version: 1.1
Name: githubflow
Version: 0.3
Summary: A command line interface to githubuses the github apis commandline.
Home-page: http://github.com/Demandcube/github-flow
Author: Steve Morin
Author-email: steve@stevemorin.com
License: UNKNOWN
Platform: UNKNOWN
Classifier: License :: OSI Approved :: GNU Affero General Public License v3
Classifier: Programming Language :: Python
Classifier: Environment :: Console
Classifier: Intended Audience :: Developers
Classifier: Topic :: Software Development :: Bug Tracking
